demo_ds_in_practice_jwzhang/__init__.py
demo_ds_in_practice_jwzhang/example.py
demo_ds_in_practice_jwzhang-0.0.1.dist-info/LICENSE
demo_ds_in_practice_jwzhang-0.0.1.dist-info/METADATA
demo_ds_in_practice_jwzhang-0.0.1.dist-info/WHEEL
demo_ds_in_practice_jwzhang-0.0.1.dist-info/top_level.txt
demo_ds_in_practice_jwzhang-0.0.1.dist-info/RECORD
