Metadata-Version: 2.1
Name: demo-ds-in-practice-jwzhang
Version: 0.0.1
Summary: Package Demo
Home-page: https://www.nus.edu.sg
Author: Jiangwei ZHANG
Author-email: zjwcarrot@gmail.com
License: UNKNOWN
Project-URL: Bug Tracker, https://www.nus.edu.sg
Platform: UNKNOWN
Classifier: Programming Language :: Python :: 3
Classifier: License :: OSI Approved :: MIT License
Classifier: Operating System :: OS Independent
Requires-Python: >=3.6
License-File: LICENSE
